LICENSE
setup.py
ctpbee_kline/__init__.py
ctpbee_kline.egg-info/PKG-INFO
ctpbee_kline.egg-info/SOURCES.txt
ctpbee_kline.egg-info/dependency_links.txt
ctpbee_kline.egg-info/requires.txt
ctpbee_kline.egg-info/top_level.txt