Metadata-Version: 2.4
Name: ctpbee_kline
Version: 0.2
Summary: ctpbee里面提供的k线生成算法
Home-page: https://www.github.com/ctpbee/ckline
Author: somewheve
Author-email: somewheve@gmail.com
License-File: LICENSE
Requires-Dist: ctpbee
Dynamic: author
Dynamic: author-email
Dynamic: home-page
Dynamic: license-file
Dynamic: requires-dist
Dynamic: summary
